MANIFEST.in
setup.py
wizard.xml
./__init__.py
./__openerp__.py
./account_wizard.py
i18n/de.po
i18n/it.po
images/config_chart_l10n_ch.jpeg
images/l10n_ch_chart.jpeg
openerp_l10n_ch.egg-info/PKG-INFO
openerp_l10n_ch.egg-info/SOURCES.txt
openerp_l10n_ch.egg-info/dependency_links.txt
openerp_l10n_ch.egg-info/requires.txt
openerp_l10n_ch.egg-info/top_level.txt
static/src/img/icon.png
sterchi_chart/account.xml
sterchi_chart/fiscal_position.xml
sterchi_chart/vat2011.xml